README.md
setup.py
hoist_prop_types/__init__.py
hoist_prop_types/__main__.py
hoist_prop_types/hoist_prop_types.py
hoist_prop_types.egg-info/PKG-INFO
hoist_prop_types.egg-info/SOURCES.txt
hoist_prop_types.egg-info/dependency_links.txt
hoist_prop_types.egg-info/entry_points.txt
hoist_prop_types.egg-info/requires.txt
hoist_prop_types.egg-info/top_level.txt