Metadata-Version: 1.0
Name: hoist-prop-types
Version: 0.1.1
Summary: Hoist your prop types to the top of a file for readibility
Home-page: https://github.com/Xesued/hoist-prop-types
Author: Nathan Norton
Author-email: nthnnrtn@gmail.com
License: UNKNOWN
Platform: UNKNOWN
